Metadata-Version: 1.2
Name: aiopluggy
Version: 0.1.5rc3
Summary: Plugin and hook calling mechanisms for python
Home-page: https://github.com/Amsterdam/aiopluggy
Author: Pieter van Beek
Author-email: aiopluggy.github.com@djinnit.com
License: MIT license
Project-URL: Documentation, https://aiopluggy.readthedocs.io/en/latest/
Project-URL: Source Code, https://github.com/Amsterdam/aiopluggy
Keywords: plugin,plug-in,async,asyncio
Platform: UNKNOWN
Classifier: Development Status :: 3 - Alpha
Classifier: Environment :: Plugins
Classifier: Framework :: AsyncIO
Classifier: Intended Audience :: Developers
Classifier: License :: OSI Approved :: MIT License
Classifier: Programming Language :: Python :: 3
Classifier: Programming Language :: Python :: 3.5
Classifier: Programming Language :: Python :: 3.6
Classifier: Programming Language :: Python :: 3.7
Classifier: Topic :: Software Development :: Libraries :: Python Modules
Requires-Python: ~=3.5
